gnobjects/__init__.py
gnobjects/time.py
gnobjects/abs/__init__.py
gnobjects/abs/id.py
gnobjects/abs/values.py
gnobjects/gwis/__init__.py
gnobjects/gwis/values.py
gnobjects/net/__init__.py
gnobjects/net/_data_pack.py
gnobjects/net/domains.py
gnobjects/net/fastcommands.py
gnobjects/net/gnTransportProtocolParser.py
gnobjects/net/objects.py
gnobjects/net/tools.py
gnobjects/net/values.py
gnobjects-0.0.38.dist-info/METADATA
gnobjects-0.0.38.dist-info/WHEEL
gnobjects-0.0.38.dist-info/top_level.txt
gnobjects-0.0.38.dist-info/RECORD
