Metadata-Version: 2.4
Name: gnobjects
Version: 0.0.38
Summary: gnobjects
Home-page: https://github.com/KeyisB/gnobjects
Author: KeyisB
Author-email: keyisb.pip@gmail.com
License: GN License v1.0
Classifier: Programming Language :: Python :: 3
Classifier: Operating System :: OS Independent
Requires-Python: >=3.12
Requires-Dist: cryptography
Requires-Dist: msgpack
Requires-Dist: pycryptodome
Requires-Dist: anyio
Requires-Dist: zstandard
Dynamic: author
Dynamic: author-email
Dynamic: classifier
Dynamic: description
Dynamic: description-content-type
Dynamic: home-page
Dynamic: license
Dynamic: requires-dist
Dynamic: requires-python
Dynamic: summary
